__init__.py
manifoldmoments/__init__.py
manifoldmoments-0.0.0.dist-info/licenses/AUTHORS.rst
manifoldmoments-0.0.0.dist-info/licenses/LICENSE.txt
manifoldmoments-0.0.0.dist-info/METADATA
manifoldmoments-0.0.0.dist-info/WHEEL
manifoldmoments-0.0.0.dist-info/top_level.txt
manifoldmoments-0.0.0.dist-info/RECORD
