Metadata-Version: 2.4
Name: manifoldmoments
Version: 0.0.0
Summary: ManifoldMoments Version 0.0.0 — Initial release.
Author-email: Liu Zhang <lz1619@princeton.edu>
Maintainer-email: Liu Zhang <lz1619@princeton.edu>
License: Copyright © 2025 Liu Zhang. All rights reserved.  
Classifier: Development Status :: 1 - Planning
Classifier: Programming Language :: Python :: 3
Classifier: License :: Other/Proprietary License
Requires-Python: >=3.7
License-File: LICENSE.txt
License-File: AUTHORS.rst
Dynamic: license-file
